.pypirc
README.rst
__init__.py
pyproject.toml
requirements.txt
setup.py
allure_pytest_mecher.egg-info/PKG-INFO
allure_pytest_mecher.egg-info/SOURCES.txt
allure_pytest_mecher.egg-info/dependency_links.txt
allure_pytest_mecher.egg-info/entry_points.txt
allure_pytest_mecher.egg-info/requires.txt
allure_pytest_mecher.egg-info/top_level.txt
examples/attachment/attachment.rst
examples/attachment/attachment_fixture.rst
examples/attachment/attachment_step.rst
examples/description/description.rst
examples/description/dynamic_description.rst
examples/display_name/display_name.rst
examples/display_name/dynamic_display_name.rst
examples/label/bdd/bdd_label.rst
examples/label/bdd/dynamic_bdd_label.rst
examples/label/bdd/select_tests_by_bdd.rst
examples/label/custom/custom_label.rst
examples/label/custom/select_tests_by_label.rst
examples/label/manual/allure_manual.rst
examples/label/severity/class_severity.rst
examples/label/severity/module_severity.rst
examples/label/severity/select_tests_by_severity.rst
examples/label/severity/severity.rst
examples/label/suite/custom_suite.rst
examples/label/suite/module_level_custom_suite.rst
examples/link/dynamic_link.rst
examples/link/link.rst
examples/parameter/dynamic_parameter.rst
examples/step/step.rst
examples/step/step_placeholder.rst
src/__init__.py
src/helper.py
src/listener.py
src/plugin.py
src/utils.py