Metadata-Version: 2.1
Name: allure-pytest-mecher
Version: 2.12.19
Summary: Modified allure-pytest
Home-page: https://github.com/allure-framework/allure-python
Author: QAMetaSoftware, Stanislav Seliverstov
Author-email: Maksim Cherniak <maximchernyak98@gmail.com>
License: MIT
Keywords: allure reporting pytest
Classifier: Programming Language :: Python :: 3
Classifier: License :: OSI Approved :: MIT License
Classifier: Operating System :: OS Independent
Requires-Python: >=3.10
